{
  "USA": [
    {"name":"Matt Freese","pos":"GK","club":"New York City FC"},
    {"name":"Chris Richards","pos":"DEF","club":"Crystal Palace"},
    {"name":"Tim Ream","pos":"DEF","club":"Charlotte FC"},
    {"name":"Mark McKenzie","pos":"DEF","club":"Toulouse"},
    {"name":"Alex Freeman","pos":"DEF","club":"Orlando City"},
    {"name":"Antonee Robinson","pos":"DEF","club":"Fulham"},
    {"name":"Tyler Adams","pos":"MID","club":"Bournemouth"},
    {"name":"Tanner Tessmann","pos":"MID","club":"Olympique Lyonnais"},
    {"name":"Weston McKennie","pos":"MID","club":"Juventus"},
    {"name":"Cristian Roldan","pos":"MID","club":"Seattle Sounders"},
    {"name":"Timothy Weah","pos":"FWD","club":"Olympique de Marseille"},
    {"name":"Diego Luna","pos":"MID","club":"Real Salt Lake"},
    {"name":"Malik Tillman","pos":"MID","club":"Bayer Leverkusen"},
    {"name":"Christian Pulisic","pos":"FWD","club":"AC Milan"},
    {"name":"Brenden Aaronson","pos":"MID","club":"Leeds United"},
    {"name":"Ricardo Pepi","pos":"FWD","club":"PSV Eindhoven"},
    {"name":"Haji Wright","pos":"FWD","club":"Coventry City"},
    {"name":"Folarin Balogun","pos":"FWD","club":"AS Monaco"}
  ],
  "PAR": [
    {"name":"Roberto Fernández","pos":"GK","club":"Club Olimpia"},
    {"name":"Orlando Gill","pos":"GK","club":"Cerro Porteño"},
    {"name":"Gustavo Gómez","pos":"DEF","club":"Palmeiras"},
    {"name":"Fabián Balbuena","pos":"DEF","club":"Grêmio"},
    {"name":"Juan José Cáceres","pos":"DEF","club":"Club Olimpia"},
    {"name":"Omar Alderete","pos":"DEF","club":"Sunderland"},
    {"name":"Junior Alonso","pos":"DEF","club":"Atlético Mineiro"},
    {"name":"Mathías Villasanti","pos":"MID","club":"Grêmio"},
    {"name":"Diego Gómez","pos":"MID","club":"Brighton & Hove Albion"},
    {"name":"Damián Bobadilla","pos":"MID","club":"São Paulo"},
    {"name":"Andrés Cubas","pos":"MID","club":"Vancouver Whitecaps"},
    {"name":"Matías Galarza Fonda","pos":"MID","club":"Talleres"},
    {"name":"Julio Enciso","pos":"FWD","club":"Strasbourg"},
    {"name":"Alejandro Romero Gamarra","pos":"MID","club":"Tigres UANL"},
    {"name":"Miguel Almirón","pos":"FWD","club":"Atlanta United"},
    {"name":"Ramón Sosa","pos":"FWD","club":"Palmeiras"},
    {"name":"Ángel Romero","pos":"FWD","club":"Corinthians"},
    {"name":"Antonio Sanabria","pos":"FWD","club":"Cremonese"}
  ],
  "AUS": [
    {"name":"Mathew Ryan","pos":"GK","club":"Levante"},
    {"name":"Joe Gauci","pos":"GK","club":"Aston Villa"},
    {"name":"Harry Souttar","pos":"DEF","club":"Sheffield United"},
    {"name":"Alessandro Circati","pos":"DEF","club":"Parma"},
    {"name":"Jordan Bos","pos":"DEF","club":"Feyenoord"},
    {"name":"Aziz Behich","pos":"DEF","club":"Melbourne City"},
    {"name":"Cameron Burgess","pos":"DEF","club":"Ipswich Town"},
    {"name":"Lewis Miller","pos":"DEF","club":"Hibernian"},
    {"name":"Miloš Degenek","pos":"DEF","club":"Al-Ittihad"},
    {"name":"Jackson Irvine","pos":"MID","club":"FC St. Pauli"},
    {"name":"Riley McGree","pos":"MID","club":"Middlesbrough"},
    {"name":"Aiden O'Neill","pos":"MID","club":"Standard Liège"},
    {"name":"Connor Metcalfe","pos":"MID","club":"FC St. Pauli"},
    {"name":"Patrick Yazbek","pos":"MID","club":"Nashville SC"},
    {"name":"Craig Goodwin","pos":"FWD","club":"Al-Wehda"},
    {"name":"Kusini Yengi","pos":"FWD","club":"Western United"},
    {"name":"Nestory Irankunda","pos":"FWD","club":"Bayern Munich"},
    {"name":"Mohamed Touré","pos":"FWD","club":"Randers FC"}
  ],
  "TUR": [
    {"name":"Uğurcan Çakır","pos":"GK","club":"Galatasaray"},
    {"name":"Mert Müldür","pos":"DEF","club":"Fenerbahçe"},
    {"name":"Zeki Çelik","pos":"DEF","club":"Roma"},
    {"name":"Abdülkerim Bardakcı","pos":"DEF","club":"Galatasaray"},
    {"name":"Çağlar Söyüncü","pos":"DEF","club":"Fenerbahçe"},
    {"name":"Merih Demiral","pos":"DEF","club":"Al-Ahli"},
    {"name":"Ferdi Kadıoğlu","pos":"DEF","club":"Brighton & Hove Albion"},
    {"name":"Kaan Ayhan","pos":"DEF","club":"Galatasaray"},
    {"name":"İsmail Yüksek","pos":"MID","club":"Fenerbahçe"},
    {"name":"Hakan Çalhanoğlu","pos":"MID","club":"Inter Milan"},
    {"name":"Orkun Kökçü","pos":"MID","club":"Benfica"},
    {"name":"Arda Güler","pos":"MID","club":"Real Madrid"},
    {"name":"İrfan Can Kahveci","pos":"MID","club":"Fenerbahçe"},
    {"name":"Yunus Akgün","pos":"MID","club":"Galatasaray"},
    {"name":"Can Uzun","pos":"FWD","club":"Eintracht Frankfurt"},
    {"name":"Barış Alper Yılmaz","pos":"FWD","club":"Galatasaray"},
    {"name":"Kerem Aktürkoğlu","pos":"FWD","club":"Fenerbahçe"},
    {"name":"Kenan Yıldız","pos":"FWD","club":"Juventus"}
  ]
}
